tornado_proxy_handlers/__init__.py
tornado_proxy_handlers/_version.py
tornado_proxy_handlers/handlers.py
tornado_proxy_handlers/server.py
tornado_proxy_handlers/tests/__init__.py
tornado_proxy_handlers/tests/test_import.py
tornado_proxy_handlers-0.0.6.dist-info/LICENSE
tornado_proxy_handlers-0.0.6.dist-info/METADATA
tornado_proxy_handlers-0.0.6.dist-info/WHEEL
tornado_proxy_handlers-0.0.6.dist-info/top_level.txt
tornado_proxy_handlers-0.0.6.dist-info/RECORD
