Metadata-Version: 2.1
Name: tornado-proxy-handlers
Version: 0.0.6
Summary: Tornado proxy handlers
Home-page: https://github.com/timkpaine/tornado-proxy-handlers
Author: Tim Paine
Author-email: t.paine154@gmail.com
License: Apache 2.0
Keywords: tornado proxy
Classifier: Development Status :: 3 - Alpha
Classifier: Programming Language :: Python :: 3
Classifier: Programming Language :: Python :: 3.6
Classifier: Programming Language :: Python :: 3.7
Classifier: Programming Language :: Python :: 3.8
License-File: LICENSE
Requires-Dist: tornado >=6.0.2
Provides-Extra: dev
Requires-Dist: tornado >=6.0.2 ; extra == 'dev'
Requires-Dist: black >=23 ; extra == 'dev'
Requires-Dist: bump2version >=1.0.0 ; extra == 'dev'
Requires-Dist: flake8 >=3.7.8 ; extra == 'dev'
Requires-Dist: flake8-black >=0.2.1 ; extra == 'dev'
Requires-Dist: mock ; extra == 'dev'
Requires-Dist: pytest >=4.3.0 ; extra == 'dev'
Requires-Dist: pytest-cov >=2.6.1 ; extra == 'dev'
Requires-Dist: Sphinx >=1.8.4 ; extra == 'dev'
Requires-Dist: sphinx-markdown-builder >=0.5.2 ; extra == 'dev'
